easy_pyoc/__init__.py
easy_pyoc/classes/__init__.py
easy_pyoc/classes/color.py
easy_pyoc/classes/config.py
easy_pyoc/classes/logger.py
easy_pyoc/classes/magic.py
easy_pyoc/qt5/OcGui.py
easy_pyoc/qt5/OcGuiRes.py
easy_pyoc/qt5/__init__.py
easy_pyoc/qt5/res/image
easy_pyoc/qt5/res/images/s
easy_pyoc/sock/__init__.py
easy_pyoc/sock/client_socket.py
easy_pyoc/sock/server_socket.py
easy_pyoc/utils/__init__.py
easy_pyoc/utils/cr4_util.py
easy_pyoc/utils/crc_util.py
easy_pyoc/utils/datetime_util.py
easy_pyoc/utils/exception_util.py
easy_pyoc/utils/flask_util.py
easy_pyoc/utils/func_util.py
easy_pyoc/utils/json_util.py
easy_pyoc/utils/knx_util.py
easy_pyoc/utils/network_util.py
easy_pyoc/utils/object_util.py
easy_pyoc/utils/package_util.py
easy_pyoc/utils/path_util.py
easy_pyoc/utils/string_util.py
easy_pyoc/utils/thread_util.py
easy_pyoc/utils/toml_util.py
easy_pyoc/utils/xml_util.py
easy_pyoc/utils/yaml_util.py
easy_pyoc-0.11.1.dist-info/LICENSE
easy_pyoc-0.11.1.dist-info/METADATA
easy_pyoc-0.11.1.dist-info/WHEEL
easy_pyoc-0.11.1.dist-info/top_level.txt
easy_pyoc-0.11.1.dist-info/RECORD
