Metadata-Version: 2.2
Name: easy_pyoc
Version: 0.11.1
Summary: 封装一些 Python 小工具，提升开发效率。
Home-page: https://github.com/one-ccs/easy_pyoc
Author: one-ccs
Author-email: one-ccs@foxmail.com
License: MIT
Classifier: Development Status :: 3 - Alpha
Classifier: Intended Audience :: Developers
Classifier: Topic :: Software Development :: Build Tools
Classifier: License :: OSI Approved :: MIT License
Classifier: Programming Language :: Python :: 3
Requires-Python: >=3
License-File: LICENSE
Requires-Dist: typing_extensions
Provides-Extra: easy-pyoc-qt5
Requires-Dist: PyQt5; extra == "easy-pyoc-qt5"
Provides-Extra: utils-flask-util
Requires-Dist: flask; extra == "utils-flask-util"
Provides-Extra: utils-yaml-util
Requires-Dist: PyYAML; extra == "utils-yaml-util"
Dynamic: author
Dynamic: author-email
Dynamic: classifier
Dynamic: description
Dynamic: description-content-type
Dynamic: home-page
Dynamic: license
Dynamic: provides-extra
Dynamic: requires-dist
Dynamic: requires-python
Dynamic: summary
